{
  "books": [
    {
      "title": "Nausea",
      "author": "Jean-Paul Sartre",
      "pagesRead": 60,
      "totalPages": 178,
      "difficulty": 6
    },
    {
      "title": "The Soundscape",
      "author": "R. Murray Schafer",
      "pagesRead": 14,
      "totalPages": 264,
      "difficulty": 7
    },
    {
      "title": "Psychotherapy East & West",
      "author": "Alan W. Watts",
      "pagesRead": 55,
      "totalPages": 205,
      "difficulty": 7
    },
    {
      "title": "Ghosts of My Life",
      "author": "Mark Fisher",
      "pagesRead": 17,
      "totalPages": 267,
      "difficulty": 6
    },
    {
      "title": "The Birth of Tragedy",
      "author": "Friedrich Nietzsche",
      "pagesRead": 4,
      "totalPages": 142,
      "difficulty": 9
    },
    {
      "title": "Fear and Trembling",
      "author": "Søren Kierkegaard",
      "pagesRead": 0,
      "totalPages": 141,
      "difficulty": 8
    },
    {
      "title": "Wherever You Go, There You Are",
      "author": "Jon Kabat-Zinn",
      "pagesRead": 0,
      "totalPages": 299,
      "difficulty": 3
    },
    {
      "title": "Oneness vs The 1%",
      "author": "Vandana Shiva",
      "pagesRead": 0,
      "totalPages": 173,
      "difficulty": 5
    },
    {
      "title": "The Patterning Instinct",
      "author": "Jeremy Lent",
      "pagesRead": 130,
      "totalPages": 430,
      "difficulty": 6
    },
    {
      "title": "The Name of the Rose",
      "author": "Umberto Eco",
      "pagesRead": 0,
      "totalPages": 576,
      "difficulty": 7
    },
    {
      "title": "Caliban and the Witch",
      "author": "Silvia Federici",
      "pagesRead": 0,
      "totalPages": 268,
      "difficulty": 7
    },
    {
      "title": "Lolita",
      "author": "Vladimir Nabokov",
      "pagesRead": 0,
      "totalPages": 317,
      "difficulty": 6,
      "estimatedPages": true
    },
    {
      "title": "She Comes First",
      "author": "Ian Kerner",
      "pagesRead": 0,
      "totalPages": 205,
      "difficulty": 2
    },
    {
      "title": "The Mountains Sing",
      "author": "Nguyễn Phan Quế Mai",
      "pagesRead": 0,
      "totalPages": 342,
      "difficulty": 4
    },
    {
      "title": "9 Out of 10 Climbers Make the Same Mistakes",
      "author": "Dave MacLeod",
      "pagesRead": 0,
      "totalPages": 164,
      "difficulty": 3
    },
    {
      "title": "Eichmann in Jerusalem",
      "author": "Hannah Arendt",
      "pagesRead": 0,
      "totalPages": 312,
      "difficulty": 7,
      "estimatedPages": true
    },
    {
      "title": "Down and Out in Paris and London",
      "author": "George Orwell",
      "pagesRead": 0,
      "totalPages": 228,
      "difficulty": 3,
      "estimatedPages": true
    },
    {
      "title": "The Fire Next Time",
      "author": "James Baldwin",
      "pagesRead": 0,
      "totalPages": 106,
      "difficulty": 4,
      "estimatedPages": true
    }
  ],
  "bookOrder": [
    0,
    15,
    17,
    1,
    13,
    11,
    16,
    2,
    3,
    4,
    14,
    5,
    7,
    6,
    8,
    9,
    12,
    10
  ],
  "readingLog": [
    {
      "date": "2026-03-17",
      "title": "Nausea",
      "pages": 1
    },
    {
      "date": "2026-03-17",
      "title": "Nausea",
      "pages": 1
    },
    {
      "date": "2026-03-18",
      "title": "Nausea",
      "pages": 10
    },
    {
      "date": "2026-03-18",
      "title": "Nausea",
      "pages": 5
    },
    {
      "date": "2026-03-20",
      "title": "Nausea",
      "pages": 10
    },
    {
      "date": "2026-03-20",
      "title": "Nausea",
      "pages": 5
    },
    {
      "date": "2026-03-20",
      "title": "Nausea",
      "pages": 15
    },
    {
      "date": "2026-03-20",
      "title": "Nausea",
      "pages": 10
    },
    {
      "date": "2026-03-20",
      "title": "Nausea",
      "pages": 5
    }
  ],
  "dailyTargets": {
    "Nausea": 15,
    "The Soundscape": 13,
    "The Mountains Sing": 18,
    "9 Out of 10 Climbers Make the Same Mistakes": 20,
    "Lolita": 15,
    "Down and Out in Paris and London": 20,
    "Eichmann in Jerusalem": 13,
    "Psychotherapy East & West": 13,
    "Ghosts of My Life": 15,
    "Wherever You Go, There You Are": 20,
    "The Fire Next Time": 18,
    "The Birth of Tragedy": 12,
    "Fear and Trembling": 12,
    "Oneness vs The 1%": 16,
    "The Patterning Instinct": 15,
    "The Name of the Rose": 16,
    "She Comes First": 23,
    "Caliban and the Witch": 13
  },
  "bookFinishDates": {
    "Nausea": "2026-03-28T16:00:00.000Z",
    "The Soundscape": "2026-04-17T16:00:00.000Z",
    "The Mountains Sing": "2026-05-06T16:00:00.000Z",
    "9 Out of 10 Climbers Make the Same Mistakes": "2026-05-15T16:00:00.000Z",
    "Lolita": "2026-06-06T16:00:00.000Z",
    "Down and Out in Paris and London": "2026-06-18T16:00:00.000Z",
    "Eichmann in Jerusalem": "2026-07-12T16:00:00.000Z",
    "Psychotherapy East & West": "2026-07-24T16:00:00.000Z",
    "Ghosts of My Life": "2026-08-10T16:00:00.000Z",
    "Wherever You Go, There You Are": "2026-08-25T16:00:00.000Z",
    "The Fire Next Time": "2026-08-31T16:00:00.000Z",
    "The Birth of Tragedy": "2026-09-12T16:00:00.000Z",
    "Fear and Trembling": "2026-09-24T16:00:00.000Z",
    "Oneness vs The 1%": "2026-10-05T16:00:00.000Z",
    "The Patterning Instinct": "2026-10-25T16:00:00.000Z",
    "The Name of the Rose": "2026-11-30T16:00:00.000Z",
    "She Comes First": "2026-12-09T16:00:00.000Z",
    "Caliban and the Witch": "2026-12-30T16:00:00.000Z"
  },
  "dailyTargetCheck": {
    "totalDaysNeeded": 289,
    "daysLeft": 289,
    "finishDate": "2026-12-30T16:00:00.000Z"
  },
  "targetBaseline": {
    "Nausea": 0,
    "The Soundscape": 14,
    "Psychotherapy East & West": 55,
    "Ghosts of My Life": 17,
    "The Birth of Tragedy": 4,
    "Fear and Trembling": 0,
    "Wherever You Go, There You Are": 0,
    "Oneness vs The 1%": 0,
    "The Patterning Instinct": 130,
    "The Name of the Rose": 0,
    "Caliban and the Witch": 0,
    "Lolita": 0,
    "She Comes First": 0,
    "The Mountains Sing": 0,
    "9 Out of 10 Climbers Make the Same Mistakes": 0,
    "Eichmann in Jerusalem": 0,
    "Down and Out in Paris and London": 0,
    "The Fire Next Time": 0
  }
}